playground/__init__.py
playground/_version.py
kitsuyui_pypi_playground-0.4.0.dist-info/METADATA
kitsuyui_pypi_playground-0.4.0.dist-info/WHEEL
kitsuyui_pypi_playground-0.4.0.dist-info/top_level.txt
kitsuyui_pypi_playground-0.4.0.dist-info/RECORD
