Metadata-Version: 2.1
Name: kitsuyui-pypi-playground
Version: 0.4.0
Summary: A playground for publishing packages to PyPI
Home-page: https://github.com/kitsuyui/pypi-playground
Author: Yui Kitsu
Author-email: kitsuyui+github@kitsuyui.com
License: BSD-3-Clause
Classifier: Development Status :: 3 - Alpha
Classifier: License :: OSI Approved :: BSD License
Requires-Python: >=3.8
